kraken_local_db/__init__.py
kraken_local_db/kraken_local_db.py
kraken_local_db/helpers/__init__.py
kraken_local_db/helpers/count_rows.py
kraken_local_db/helpers/delete.py
kraken_local_db/helpers/get.py
kraken_local_db/helpers/index.py
kraken_local_db/helpers/init_db.py
kraken_local_db/helpers/post.py
kraken_local_db/helpers/search.py
kraken_local_db-0.0.7.dist-info/LICENSE.txt
kraken_local_db-0.0.7.dist-info/METADATA
kraken_local_db-0.0.7.dist-info/WHEEL
kraken_local_db-0.0.7.dist-info/top_level.txt
kraken_local_db-0.0.7.dist-info/RECORD
