Metadata-Version: 2.1
Name: kraken-local-db
Version: 0.0.7
Summary: Kraken local sqlite database for tings
Home-page: https://github.com/tactik8/krakenlocaldb
Author: Tactik8
Author-email: info@tactik8.com
License: MIT
Classifier: License :: OSI Approved :: MIT License
Classifier: Programming Language :: Python :: 3
Classifier: Programming Language :: Python :: 3.8
License-File: LICENSE.txt
